alarm/__init__.py
alarm/nine_turn.py
data/__init__.py
data/akshare.py
data/fushare.py
data/tushare.py
x_stock/__init__.py
x_stock-0.1.8.dist-info/LICENSE
x_stock-0.1.8.dist-info/METADATA
x_stock-0.1.8.dist-info/WHEEL
x_stock-0.1.8.dist-info/top_level.txt
x_stock-0.1.8.dist-info/RECORD
