Metadata-Version: 2.1
Name: x-stock
Version: 0.1.8
Summary: 个人股票分析工具
Home-page: https://github.com/yourusername/x-stock
Author: chuck xue
Author-email: 2254379984@qq.com
Classifier: Programming Language :: Python :: 3
Classifier: License :: OSI Approved :: MIT License
Classifier: Operating System :: OS Independent
Requires-Python: >=3.7
License-File: LICENSE
Requires-Dist: akshare
Requires-Dist: pandas
Requires-Dist: numpy
Requires-Dist: matplotlib
